securitytxt/__init__.py
securitytxt/__version__.py
securitytxt/core.py
securitytxt-0.0.2.dist-info/LICENSE
securitytxt-0.0.2.dist-info/METADATA
securitytxt-0.0.2.dist-info/WHEEL
securitytxt-0.0.2.dist-info/top_level.txt
securitytxt-0.0.2.dist-info/RECORD
