Metadata-Version: 2.1
Name: securitytxt
Version: 0.0.2
Summary: My short description for my project.
Home-page: https://github.com/myles/python-securitytxt
Author: Myles Braithwaite
Author-email: python-securitytxt@mylesbraithwaite.org
License: MIT
Platform: UNKNOWN
Classifier: License :: OSI Approved :: MIT License
Classifier: Programming Language :: Python
Classifier: Programming Language :: Python :: 3
Classifier: Programming Language :: Python :: 3.6
Classifier: Programming Language :: Python :: Implementation :: CPython
Classifier: Programming Language :: Python :: Implementation :: PyPy
Requires-Python: >=3.6.0
Requires-Dist: requests
